{"knowledge-domains_biology_有氧与无氧呼吸.md":"7SiFqkN_","knowledge-domains_history_readme.md":"nebXieyI","life_coffee_coffee-6.md":"P9nYSBDS","knowledge-domains_index.md":"qlFAtrLl","life_coffee_coffee-5.md":"-QbmEHWf","travel_fuzhou-2.md":"BNB_IOtp","life_coffee_coffee-4.md":"g0yygRQc","my-blogs_readme.md":"7G2av36U","life_coffee_coffee-1.md":"svdt7s4I","knowledge-domains_history_cah_唐.md":"A_MzM_pD","life_coffee_coffee-3.md":"xwTuvWq6","life_coffee_coffee-2.md":"u_f0AZQf","knowledge-domains_history_cmh_抗日战争.md":"CwDCUqnC","knowledge-domains_math_複素数.md":"kkGyxnML","knowledge-domains_history_cah_北魏.md":"0F64VvzU","knowledge-domains_biology_細胞呼吸.md":"QNs0Rj4x","knowledge-domains_biology_細胞呼吸のプロセス.md":"pg0Izju_","knowledge-domains_japanese_readme.md":"9qAhgQ48","knowledge-domains_history_cah_明.md":"RH4Xl7lz","knowledge-domains_history_cah_隋.md":"puh05hIX","knowledge-domains_biology_readme.md":"Agxq7w4x","knowledge-domains_history_cah_汉.md":"agWuvQ_U","api-examples.md":"JzlcDNlI","knowledge-domains_history_cmh_国共内战.md":"em6SgITy","knowledge-domains_math_ベクトル.md":"6l4zt4ic","knowledge-domains_history_cah_西周.md":"qZkgP0KM","life_readme.md":"rTnVkw04","my-blogs_随笔1.md":"0tRPWAOr","markdown-examples.md":"VQuz5FUR","life_coffee_coffee-7.md":"4eBtPilH","my-blogs_index.md":"Kouyf5nf","my-blogs_随笔2.md":"YrQmeuWG","knowledge-domains_math_readme.md":"Jsg8ISAj","travel_fuzhou-1.md":"NIzmrMTh","knowledge-domains_japanese_て形.md":"D_lMRtPI","knowledge-domains_history_cmh_清.md":"bnHOFtSp","my-blogs_历史做题心得.md":"8NHGIezv","my-blogs_因果论.md":"GHS4NozJ","knowledge-domains_readme.md":"DO2_4UoW","knowledge-domains_biology_单糖.md":"K6fVTB2L","index.md":"6IAGh-6v","knowledge-domains_biology_磷脂.md":"OUyGEVy_","knowledge-domains_history_cah_科挙.md":"IzB7IPEM","travel_readme.md":"8SXx2_Iz","knowledge-domains_history_cah_两宋.md":"Ryr5GC9w","knowledge-domains_biology_多糖.md":"FsPj08XM","knowledge-domains_biology_リボソームとミトコンドリア.md":"ky4wLXVj"}
